parse_helper/__init__.py
parse_helper/parser.py
parse_helper/scripts/__init__.py
parse_helper/scripts/ddg.py
parse_helper/scripts/download_file_as.py
parse_helper/scripts/download_files.py
parse_helper/scripts/soup.py
parse_helper-0.1.22.dist-info/LICENSE.txt
parse_helper-0.1.22.dist-info/METADATA
parse_helper-0.1.22.dist-info/WHEEL
parse_helper-0.1.22.dist-info/entry_points.txt
parse_helper-0.1.22.dist-info/top_level.txt
parse_helper-0.1.22.dist-info/RECORD
