Metadata-Version: 2.1
Name: parse-helper
Version: 0.1.22
Summary: Helpers to fetch & parse text on pages with requests, lxml, & beautifulsoup4
Home-page: https://github.com/kenjyco/parse-helper
Download-URL: https://github.com/kenjyco/parse-helper/tarball/v0.1.22
Author: Ken
Author-email: kenjyco@gmail.com
License: MIT
Keywords: parse,requests,duckduckgo,cli,command-line,download,soup,beautifulsoup,lxml,helper,kenjyco
Platform: UNKNOWN
Classifier: Development Status :: 3 - Alpha
Classifier: Environment :: Console
Classifier: Environment :: Web Environment
Classifier: Intended Audience :: Developers
Classifier: License :: OSI Approved :: MIT License
Classifier: Operating System :: MacOS :: MacOS X
Classifier: Operating System :: POSIX :: Linux
Classifier: Programming Language :: Python :: 3.5
Classifier: Programming Language :: Python
Classifier: Topic :: Software Development :: Libraries
Classifier: Topic :: Text Processing :: Markup :: HTML
Classifier: Topic :: Text Processing :: Markup :: XML
Classifier: Topic :: Utilities
License-File: LICENSE.txt
Requires-Dist: beautifulsoup4
Requires-Dist: click
Requires-Dist: fs-helper
Requires-Dist: input-helper
Requires-Dist: lxml
Requires-Dist: requests
